setup.py
bin/play_monty_hall_cli.py
bin/play_monty_hall_web.py
monty_hall_game/__init__.py
monty_hall_game/game_exceptions.py
monty_hall_game/monty_hall_game.py
monty_hall_game.egg-info/PKG-INFO
monty_hall_game.egg-info/SOURCES.txt
monty_hall_game.egg-info/dependency_links.txt
monty_hall_game.egg-info/top_level.txt