Metadata-Version: 1.0
Name: monty-hall-game
Version: 0.0.1
Summary: A game implementation of the Monty Hall problem.
Home-page: UNKNOWN
Author: Simon Funke
Author-email: simon@simula.no
License: BSD
Platform: UNKNOWN
